{
  "ClassName": "HouseModel",
  "SuperClasses": [],
  "SubClasses": [],
  "Description": "Es una clase que representa el modelo de una casa en nuestro sistema.",
  "Attributes": [
    {
      "Name": "grid",
      "Description": "Representa la cuadrícula que define el entorno de la casa."
    }
  ],
  "Responsibilities": [
    {
      "Name": "Inicializar el entorno",
      "Collaborator": "HouseEnv, HouseView, json"
    },
    {
      "Name": "Cargar datos del entorno",
      "Collaborator": ""
    },
    {
      "Name": "Añadir medicamentos a un objeto específico",
      "Collaborator": ""
    },
    {
      "Name": "Obtener la cantidad de medicamentos de un objeto específico",
      "Collaborator": ""
    },
    {
      "Name": "Obtener el estado de apertura de un objeto específico",
      "Collaborator": ""
    },
    {
      "Name": "Establecer el estado de apertura de un objeto en específico",
      "Collaborator": ""
    },
    {
      "Name": "Obtener la capacidad máxima de un objeto en específico",
      "Collaborator": ""
    },
    {
      "Name": "Cambiar la posición de un objeto",
      "Collaborator": ""
    },
    {
      "Name": "Obtener el valor de la posición en la cuadrícula",
      "Collaborator": ""
    },
    {
      "Name": "Establecer el valor de la posición en la cuadrícula",
      "Collaborator": ""
    },
    {
      "Name": "Eliminar un valor específico de la cuadrícula",
      "Collaborator": ""
    },
    {
      "Name": "Obtener la posición de un valor específico en la cuadrícula",
      "Collaborator": ""
    }
  ]
}
